[
    {
        "version": "3102",
        "shortversion": "v2.4.5",
        "title": "YMusic Android",
        "timestamp": 1529168115,
        "appsize": 6747035,
        "notes": "<h2>Urgent update v2.4.5</h2>\n\n<h3>Update via:</h3>\n\n<p><a href=\"https://ymusic.en.uptodown.com/android/download\"><img src=\"https://music-app.me/img/uptodown_icon.png\" width=\"150\" /><a href=\"https://labs.xda-developers.com/store/app/com.kapp.youtube.final\"><img src=\"https://music-app.me/img/xda_labs_icon.png\" width=\"150\" /></a><a href=\"https://drive.google.com/a/hcmut.edu.vn/uc?id=0B1-d3Xs9yeFHT2pKeWNrdWpJX1U&amp;export=download\"><img src=\"https://music-app.me/img/google_drive_icon.png\" width=\"150\" /></a></p>\n\n<ul>\n<li><strong>Urgent update:</strong> older version won&#39;t work after June 18, 2018.</li>\n<li>Fix startup crash Android 4.x</li>\n</ul>",
        "mandatory": false,
        "external": false,
        "device_family": null,
        "id": 223,
        "app_id": 344882,
        "minimum_os_version": "4.1"
    },
    {
        "version": "3098",
        "shortversion": "v2.4.4",
        "title": "YMusic Android",
        "timestamp": 1525168600,
        "appsize": 6745939,
        "notes": "<h2>Version 2.4.4</h2>\n\n<ul>\n<li>Add Features: \n\n<ul>\n<li>Set playback speed</li>\n<li>Share YouTube link</li>\n<li>Share local music file</li>\n</ul></li>\n<li>Update: Load all YouTube playlist of your account instead of limited at 50 items.</li>\n<li>Fix crash on startup (android 7.0)</li>\n</ul>\n",
        "mandatory": false,
        "external": false,
        "device_family": null,
        "id": 219,
        "app_id": 344882,
        "minimum_os_version": "4.1"
    },
    {
        "version": "3092",
        "shortversion": "v2.4.1",
        "title": "YMusic Android",
        "timestamp": 1521476966,
        "appsize": 6740713,
        "notes": "<h2>Version 2.4.1</h2>\n\n<ul>\n<li>Fix load Popular videos error</li>\n<li>Fix play video via share intent not working sometime</li>\n<li>Update some icons</li>\n</ul>\n",
        "mandatory": false,
        "external": false,
        "device_family": null,
        "id": 211,
        "app_id": 344882,
        "minimum_os_version": "4.1"
    },
    {
        "version": "3090",
        "shortversion": "v2.4.0",
        "title": "YMusic Android",
        "timestamp": 1519223576,
        "appsize": 6887132,
        "notes": "<h2>Version 2.4.0</h2>\n\n<ul>\n<li><strong>Add Setting options: MP3 encoder and bitrate</strong></li>\n<li>Add remove songs feature (may not work with songs store in SD card)</li>\n<li>Fix can&#39;t play songs have same name</li>\n<li>Fix album art display wrong</li>\n<li>Fix some login issues and app crash</li>\n</ul>\n",
        "mandatory": false,
        "external": false,
        "device_family": null,
        "id": 206,
        "app_id": 344882,
        "minimum_os_version": "4.1"
    }
]